pirep.py
pirep-0.0.2.dist-info/LICENSE
pirep-0.0.2.dist-info/METADATA
pirep-0.0.2.dist-info/WHEEL
pirep-0.0.2.dist-info/top_level.txt
pirep-0.0.2.dist-info/RECORD
