Metadata-Version: 2.1
Name: pirep
Version: 0.0.2
Summary: Python Integer Representations & Arithmetic Library
Home-page: https://github.com/smurphik/pirep
Author: Denis Stepnov
Author-email: stepnovdenis@gmail.com
License: MIT
Keywords: field bitwise representation arithmetic
Platform: UNKNOWN
Classifier: Development Status :: 3 - Alpha
Classifier: License :: OSI Approved :: MIT License
